geomeffibem/__init__.py
geomeffibem/boundingbox.py
geomeffibem/plane.py
geomeffibem/polyhedron.py
geomeffibem/surface.py
geomeffibem/transformation.py
geomeffibem/vertex.py
geomeffibem-0.1.6.dist-info/LICENSE
geomeffibem-0.1.6.dist-info/METADATA
geomeffibem-0.1.6.dist-info/WHEEL
geomeffibem-0.1.6.dist-info/RECORD
